itikz/__init__.py
itikz-0.1.5.dist-info/AUTHORS.rst
itikz-0.1.5.dist-info/LICENSE
itikz-0.1.5.dist-info/METADATA
itikz-0.1.5.dist-info/WHEEL
itikz-0.1.5.dist-info/entry_points.txt
itikz-0.1.5.dist-info/top_level.txt
itikz-0.1.5.dist-info/RECORD
