Metadata-Version: 2.1
Name: itikz
Version: 0.1.5
Summary: Cell magic for PGF/TikZ-to-SVG rendering in Jupyter
Home-page: https://github.com/jbn/itikz
Author: John Bjorn Nelson
Author-email: jbn@abreka.com
License: MIT license
Keywords: itikz
Platform: UNKNOWN
Classifier: Development Status :: 2 - Pre-Alpha
Classifier: Intended Audience :: Developers
Classifier: License :: OSI Approved :: MIT License
Classifier: Natural Language :: English
Classifier: Programming Language :: Python :: 2
Classifier: Programming Language :: Python :: 2.7
Classifier: Programming Language :: Python :: 3
Classifier: Programming Language :: Python :: 3.4
Classifier: Programming Language :: Python :: 3.5
Classifier: Programming Language :: Python :: 3.6
Classifier: Programming Language :: Python :: 3.7
